{"cameraMode":{"drawMode":0,"name":"Shaded","section":"Shading Mode"},"sceneLighting":false,"audioPlay":false,"sceneViewState":{"m_AlwaysRefresh":false,"showFog":false,"showSkybox":false,"showFlares":true,"showImageEffects":true,"showParticleSystems":true,"showVisualEffectGraphs":true,"m_FxEnabled":true},"in2DMode":false,"pivot":{"x":5.760010242462158,"y":2.2390365600585939,"z":4.742027759552002},"rotation":{"x":-0.06183512881398201,"y":0.9190447330474854,"z":-0.3542155921459198,"w":-0.16138286888599397},"size":1.9651979207992554,"orthographic":false}